README.md
setup.py
ArkPrice/__init__.py
ArkPrice/price.py
ArkPrice.egg-info/PKG-INFO
ArkPrice.egg-info/SOURCES.txt
ArkPrice.egg-info/dependency_links.txt
ArkPrice.egg-info/not-zip-safe
ArkPrice.egg-info/requires.txt
ArkPrice.egg-info/top_level.txt
tests/__init__.py
tests/test_price.py