Metadata-Version: 1.2
Name: ArkPrice
Version: 0.1.0
Summary: Fetch the current price of Ark
Home-page: https://github.com/Highjhacker/arkprice
Author: Highjhacker
Author-email: jolanbeer@gmail.com
License: MIT
Keywords: Ark python api price markets cryptocurrency
Platform: UNKNOWN
Classifier: Development Status :: 4 - Beta
Classifier: Intended Audience :: Developers
Classifier: Topic :: Software Development :: Build Tools
Classifier: License :: OSI Approved :: MIT License
Requires-Python: >=3
